Metadata-Version: 2.1
Name: cudf-cu12
Version: 25.10.0
Summary: cuDF - GPU Dataframe
Author: NVIDIA Corporation
License: Apache-2.0
Classifier: Intended Audience :: Developers
Classifier: Topic :: Database
Classifier: Topic :: Scientific/Engineering
Classifier: License :: OSI Approved :: Apache Software License
Classifier: Programming Language :: Python
Classifier: Programming Language :: Python :: 3.10
Classifier: Programming Language :: Python :: 3.11
Classifier: Programming Language :: Python :: 3.12
Classifier: Programming Language :: Python :: 3.13
Project-URL: Homepage, https://github.com/rapidsai/cudf
Project-URL: Documentation, https://docs.rapids.ai/api/cudf/stable/
Requires-Python: >=3.10
Requires-Dist: cachetools
Requires-Dist: cuda-python<13.0a0,>=12.9.2
Requires-Dist: cuda-toolkit[nvcc,nvrtc]==12.*
Requires-Dist: cupy-cuda12x>=13.6.0
Requires-Dist: fsspec>=0.6.0
Requires-Dist: libcudf-cu12==25.10.*
Requires-Dist: numba-cuda[cu12]<0.20.0a0,>=0.19.1
Requires-Dist: numba<0.62.0a0,>=0.60.0
Requires-Dist: numpy<3.0a0,>=1.23
Requires-Dist: nvtx>=0.2.1
Requires-Dist: packaging
Requires-Dist: pandas<2.4.0dev0,>=2.0
Requires-Dist: pyarrow!=17.0.0,>=15.0.0; platform_machine == "aarch64"
Requires-Dist: pyarrow>=15.0.0; platform_machine == "x86_64"
Requires-Dist: pylibcudf-cu12==25.10.*
Requires-Dist: rich
Requires-Dist: rmm-cu12==25.10.*
Requires-Dist: typing_extensions>=4.0.0
Provides-Extra: test
Requires-Dist: cramjam; extra == "test"
Requires-Dist: fastavro>=0.22.9; extra == "test"
Requires-Dist: hypothesis>=6.131.7; extra == "test"
Requires-Dist: msgpack; extra == "test"
Requires-Dist: pytest; extra == "test"
Requires-Dist: pytest-benchmark; extra == "test"
Requires-Dist: pytest-cases>=3.8.2; extra == "test"
Requires-Dist: pytest-cov; extra == "test"
Requires-Dist: pytest-xdist; extra == "test"
Requires-Dist: scipy; extra == "test"
Requires-Dist: tzdata; extra == "test"
Requires-Dist: zstandard; extra == "test"
Provides-Extra: pandas-tests
Requires-Dist: hypothesis>=6.131.7; extra == "pandas-tests"
Requires-Dist: ipython; extra == "pandas-tests"
Requires-Dist: pandas[clipboard,compression,computation,excel,feather,fss,hdf5,html,output-formatting,parquet,performance,plot,pyarrow,spss,test,xml]; extra == "pandas-tests"
Requires-Dist: pytest-reportlog; extra == "pandas-tests"
Provides-Extra: cudf-pandas-tests
Requires-Dist: certifi; extra == "cudf-pandas-tests"
Requires-Dist: ipython; extra == "cudf-pandas-tests"
Requires-Dist: jupyter_client; extra == "cudf-pandas-tests"
Requires-Dist: nbconvert; extra == "cudf-pandas-tests"
Requires-Dist: nbformat; extra == "cudf-pandas-tests"
Requires-Dist: openpyxl; extra == "cudf-pandas-tests"
Requires-Dist: pytest-rerunfailures!=16.0.0; extra == "cudf-pandas-tests"
